{
  "version": "6",
  "dialect": "sqlite",
  "id": "6b2d4429-4ef7-4ff2-9b92-2534c008ab06",
  "prevId": "9254e3c0-381b-4b12-bfab-1a3cd028c4f8",
  "tables": {
    "nutrition_rules": {
      "name": "nutrition_rules",
      "columns": {
        "id": {
          "name": "id",
          "type": "text",
          "primaryKey": true,
          "notNull": true,
          "autoincrement": false
        },
        "name": {
          "name": "name",
          "type": "text(255)",
          "primaryKey": false,
          "notNull": false,
          "autoincrement": false
        },
        "nameF": {
          "name": "nameF",
          "type": "text(255)",
          "primaryKey": false,
          "notNull": false,
          "autoincrement": false
        },
        "code": {
          "name": "code",
          "type": "text(100)",
          "primaryKey": false,
          "notNull": true,
          "autoincrement": false
        },
        "formula": {
          "name": "formula",
          "type": "text",
          "primaryKey": false,
          "notNull": true,
          "autoincrement": false
        },
        "createdAt": {
          "name": "createdAt",
          "type": "text",
          "primaryKey": false,
          "notNull": true,
          "autoincrement": false,
          "default": "CURRENT_TIMESTAMP"
        },
        "updatedAt": {
          "name": "updatedAt",
          "type": "text",
          "primaryKey": false,
          "notNull": true,
          "autoincrement": false,
          "default": "CURRENT_TIMESTAMP"
        }
      },
      "indexes": {
        "nutrition_rules_code_unique": {
          "name": "nutrition_rules_code_unique",
          "columns": [
            "code"
          ],
          "isUnique": true
        }
      },
      "foreignKeys": {},
      "compositePrimaryKeys": {},
      "uniqueConstraints": {}
    }
  },
  "enums": {},
  "_meta": {
    "schemas": {},
    "tables": {},
    "columns": {}
  },
  "internal": {
    "indexes": {}
  }
}